{
"wtmptckj6b6dqemky3nyfdre":["celso-nvs","Celso Nvs"],
"ryzlhtbpgz6atw3yyalsfmf5":["nvs.xyz","nvs"],
"csipmkpmpgdpsysxnrm65dsq":["nvsofts","NV"],
"hgfnxparw6w2kttauoj7yhs3":["nvsceci","Cecília "],
"aguru5o25fknzijfrxa4gfso":"nvspirit0",
"ocixxgweeh7s64gqjb3pezyw":["nvs","NVS"],
"sa2wdvquirkibwww2vbyqrwn":["nvskinspa","NV Skin Spa"],
"d7pl6gl22pspwldr2pqn3psg":["nvssins","The Hero of Crime"],
"b7ut22hk6ahp2y2my7auprbs":["nvsx","Nick"],
"4jfsxeklwthpcp7eebefslrm":"nvshep72",
"kcmjxoktugrzvekl6lmtbfz3":"nvspirit2",
"smo5hih77xqzi7c7ql2enhms":"nvsbl",
"memqvto3rty3w3l2ym2bkhxn":["nvsbll","Nvsbl"],
"i7fsgeyxqvdcmgaq4p4oyhb3":["nvseismolab","Nevada Seismological Laboratory"],
"v6ttei42lpexuuhrjnvtefyf":"nvspirit20",
"qmor7veowubedg5qs6d64dzq":["nvsharon","Sharonsayswhat"],
"vzmrdwx2ilug7xpvprrjgnwy":["nvs14","Iker 'NVS14'"]
}
