{
"jouk26haiar2pvuzownewi5m":["0918nobita","Kodai"],
"4bql5jrbxkqnypvy562dizar":["1niemand","Niemand/Nobody"],
"y67s32qt35m7u4ea67inqzxb":["0nobeka","あけぼの"],
"al7pkxzursrnz4vrujmfqbte":["73myrda","Myrda (MisterNobody73)"],
"o66c5rjb5rkzk4edq5b3dw52":["abduljeleel","We're Noble"],
"im4mlelk32g3ppiirt2ztar6":["achangeofpants","`Nobody"],
"pbneomfdndj2y3t3ctdcrrgj":["aintslayed","Ain’t Slayed Nobody"],
"celpdme332tjwrsucdl26z4a":["akanobodyy","AKA Nobodyy"],
"aiesbm4czmrxw5ckxcedr6aq":["akawomp","NobuBalls "],
"zfbmltmr2hueqafpduzgh3rl":["alexanderedward","Barnes & noble copy of the Beatles “1” on vinyl"],
"akgfyf4wkc7xapc6wpp4ehsk":["alissonnobrien","Alisson Nobrien"],
"5bltoqvxwqxsmbzhvdeiojwj":["altofjolo","James Nobody"],
"otvyhk2wwm43avq26sezu4ds":["amiliafox","Nobody "],
"524fuatudenxyf56babk27kz":["andyroodee","nobody"],
"7weoksihvj3soakpzbrnjtek":["aqayenobody","Mr.Nobody"],
"c5ub3ns5u5v553izgsblqrer":["arjannobel","Arjan Nobel"],
"lwunxpoppfktkqv3r67jq2wi":["arinoblewrites","Ari Noble (Metajoker)"],
"cchdygg3lwojfgcbvlvfas5c":["astral-nobody","Temporal Tempo"],
"mtepw4cvbmdvu7zygmm5xbop":["averagemarcus","Marcus Noble"],
"sor37fl3gfe2mg2zdxedt2oi":["azhekdebs","nobody"],
"izdczezo3yjiejnk2jdoilbe":["b3nobi","Kenobi"],
"adp6wp3pyouegi73tvgc3rkr":["barnesandnoble","Barnes & Noble"],
"lmdfnvwaexfsocnbvippa7gk":["bashful","Bashful Nobody"],
"fiermnrodwdkqqm6zzs4vjor":["barretnobelfit","Barret Nobel | DadFit Coach"],
"4yg2bkv6ogk5wd4lqvykxm4g":["bexnobody","Bex Nobody"],
"nkdoxuupoyvbqg32bz2ws4tz":["benobi","Nobi"],
"kq7bsimm4y2znfwwm7zx43co":["benjaminsnoble","Ben Noble"],
"r5fcm3zkcgvjwtdzbuj72twj":["birgitkp","Birgit #nobullshit"],
"kndez5slnxgjmfjmokrvtscc":"b-noble",
"wbl5wisp4c7biki3kyos2wse":["bonnob","BON_NOB"],
"wudelcem4drftot5u2foztpb":["brubs1701","Bruna Nobrega"],
"rhzai6sghkz5tpovjalj26jj":["candidanobre","Cândida Nobre"],
"stbwrreyzkyveoquuda2fjyu":["carlosdca","Nobody"],
"wdii4psrgtbdvyteieyjb3mi":["cdust14","No Longer A Nobody"],
"t52bznpofanzuziq4akjf6hp":["chirose","Rosemary Noble"],
"wxzbax4av22vn5bqftw5pxbg":["chubnobby","Nobby"],
"d3j2pychhk3guki3por5beus":["christophenoblet","Christophe NOBLET "],
"jysutst6ae26wtija67dtugj":["citron-nobel","Citron Nobel"],
"kiutnwrnq7qbf4rfn6j4tkpr":["cjuanitanoble","CJuanitaNoble"],
"ttyiakqil3lerwaz7ouymnqi":["cniofficial","Noble "],
"f7ylilzcavszpdxzqifjoefs":["completelynobody","CompletelyNobody"],
"gxkzvwxfbss3ydmriock4g6t":["coffeecarbuncle","Nobutaka Fairclough ~Coffee&Carbuncles Host~"],
"vjbztg3viq27zu6fm2jey2p5":["codynoble","Cody Noble"],
"rnr45sjvodiuhkygehlopnx4":["conradnobert","Conrad Nobert"],
"sxrjeecfejt5jom7zhge7jb4":["cowsersenpai","Cowser Nobu"],
"ii5egtllw76gjhadgeqsxixt":["cosmicnobody","💀🎃🌌Cosmic Nobody🌌🎃💀"],
"ozzuhxgyysuizmjxszrxng3o":["craignobbs","Craig Nobbs"],
"dj3ccupbqlj7xvhizhij6oy6":["curseten","Nobody you’d know"],
"7lmuc7e6siwbmaolhgpjteza":["curtisperry","Nobody"],
"aunu55rbijjf4n4ryh3zxdi7":["davidpnoble","David Noble 🏴󠁧󠁢󠁷󠁬󠁳󠁿"],
"mi6nsdcidsxpnbf6i3bkq3ip":["danilonobrega","Danilo Nobrega - arte e magia"],
"nbsa47i4zmyeb4ybc5lbvspf":["dailmaudsleyn","Dail Maudsley-Noble"],
"v5lq5z4g6tlkmhg7hhzx3ody":["daxstrife","Nobody Likes Dax"],
"iic6nqbbqpukbfabtkpjooha":["dannoble","Daniel Noble "],
"tvbsingzklm3tqupjcmjlx2t":["dannobrega","Daniel Nobrega"],
"d5r5rrxvlrzei3qoy6y3jrr4":["ddoncer","Nobody1974"],
"enepnsbuwaz6b6zff3q7vu4z":["denobel","Jacob DIE!Nobel"],
"34bouvtmnfh7rjs534gxgyt7":["dearnobody.substack.com","dear nobody"],
"iqp7btjn6rphxpninqhyeahw":["dearn0b0dy","Dear Nobody"],
"h3r4hw6gmvhz4iuyl5yqueid":["dedlewd","Some f*ckin nobody 🔞"],
"xsduto5fohtskcksqp62g7nw":["dee4nobeer","カンカンが苦学"],
"gxumi5bq5j6nykc2rrtead5e":["dimitko","MrNobody"],
"ihjwz3a76dmcnyd3ud7lh7nr":["dianobre.substack.com","Dia Nobre"],
"gvswskza5d6c2exak5kxnduy":["divsel","nobody"],
"vwigzihik7ykxpbxyu2p4vnm":["digihis","Nobuhiko Kikuchi"],
"ki2wqlkspy6nm5rs2q6mucfm":"digital-nobody",
"k5f4a65ejkrk3syr4vvg4sxp":["discordant","Nobody Special"],
"bcmdghqglo3miidnf3lmlbr3":["diszkohold","Nobodaddy"],
"bqwi25qbp3c6h5ohnbwqk2c4":["dl8laq","Nobby"],
"o5hqe3wq3wh5ymes2x3hwuzb":["douglasnoble","Douglas Noble"],
"rkmdpup5f3z7hwhnrdirbdop":["dominicnoble","Dom Noble"],
"vnwtacoy7eyp64jvrtzza2wk":["doublen517","Mr. Nobody"],
"q3hki7hayz2catsqjojfgxhm":["dogmtg","Nobody Knows I'm A Dog 🏳️‍🌈"],
"xwh4frl5e2xjw6ubf2vouucv":["drnobody24","Mr. Nobody"],
"ljj5g2gtgphxgxp5xxpgq32y":["eisnoble","E Noble (ze/they/she)"],
"zyi6tfxvznqhekdwaibsamyp":["endersonnobre","Enderson Nobre"],
"napg3wx4hjjrmzzhuz6i4kpv":["ericanoble","Erica Noble"],
"25sqmv6mlbq77zgkqmkg3jw3":["espiritunoble","Espiritu Noble "],
"htn72kqeaokhpdtws2u7xf4d":["fatcr0w","Nobody important"],
"krakf4yoi6pgupylfap3m2gb":["fargothpilled","nobell🌙"],
"vsclngugqbf6fcfvvadmqdx7":["fardin574","Fardin Nobakht"],
"2j4k6nldjtc6ypj3mxx3qk6l":["faebius","Fabien Noblet"],
"vcssegsdkj33zezanpccwzr4":["fctry2","Joshua Noble"],
"iuijssc7badvy3ophp2irylx":["feb19","Nobuhiro Takahashi"],
"pgjvewuwbcvbfjtlzwste7kc":["felixml","ain't nobody"],
"ds5xefc5tejpyjfytyjfaf5w":["ffo-nobooody","ffo_nobooody @ Twitch"],
"kmw7kxcwrvic3ganqrtxsfam":["fgnoblecourt","FG Noble Court"],
"qss25yqk4rqbxskjhw4ksiuj":["fivek","i'm nobody"],
"rng4ot5effv252jqj7uuapqh":["fionafnoble","Fiona Noble"],
"gw4aohweun6mhvhtu6464gtj":["flyingnobita","Flying Nobita"],
"s2auh25rsykqorfjwel2m2if":["frambley1","Nobody Ever"],
"fbfbngpa47osh5mgurptyzs6":["garchomped","Noble6inCave"],
"gd7cq4ugpry5jqj2jbp3dqf5":["gerald-nobodi","Gérald Nobodi"],
"spyva3vdhr77ysbj4qrs4wl5":["gluber","Glauber Nobrega"],
"gmxqwesbi3r24o44wkbr5p3i":["gnobre","\"gê\" nobre"],
"4znhl7xk235aq66psvjz3mgp":["gnovyck","Grigory Nobunyaga Rasputin"],
"dft4hvu7zkyfajcsnyxyeh3j":"g-nob",
"7ebnmsusl3r2uuaf24igiazh":["gnoblet","Guillaume Noblet"],
"fus5iisspmsgsazaihay42fb":["goncalonobre","Gonçalo Nobre"],
"6ct5xfnxmvy7mpuuszyow3xh":["gretagerwigs","cher(nobyl)"],
"6vfxfzarxjaxqjkonffc5bsq":["greennoob","GreenNoble OriginalBrother ☆ 23"],
"7yh5bhtx2yydirlxe2t4vwmu":["grumpyandbroke","Tore Nobiling"],
"c4iu6wxa2ogoylturfkr4kwd":["gregornobis","Gregor Nobis"],
"a4rxhi4yv73uurjzkeopqqg7":["guilhermenobrega","Guilherme Nobrega"],
"of2p437rk4ijsiq47ilqbuus":["haggie21","Noboru Hagino (Rheumatology)"],
"3ckl6pb5j5bypryb4ujcxnpu":["hashtagdta","nobody"],
"x6persr4atmzt2v7aneldwwo":["haya-sann","Nobuo Hayashi"],
"hfpz2xpb7lzhw6lnx34dqatr":["hirap","NobuakiHirai"],
"kb2smvj3ytnoad7v7d3b5qxp":["hijinks","Nobody"],
"a6qhmrq53miz7me66rz76etl":["hideyoshipubes","Toyotomi Hideyoshi x Oda Nobunaga"],
"bnnj3odgm3og37tdtk7vazyl":["holzkasper","Nobody on the bouncy castle"],
"5ptigvp6udsdftbn2dyqjvnc":["iamsysop.liquidbbs.net","nobody important"],
"2dsp7jbcvureiqp5w2lmxbyj":["ignobledraws","Noble // Rowan "],
"a4fv4t4765lb2uvdyu637ydg":["imjustnobody","Just nobody"],
"uxvz7uyjp2xht6d64mppb3si":["initialresponse","Mr Nobody "],
"q6j4yrjl3mapt5qnf3ftsc6x":["invulnerable","Nobody"],
"slf57ty3pffgjtcf3q4tab5z":["isperfect79","Nobody "],
"b5ju737oyhk4sxpqijoiagac":["itskhanom","Nobody "],
"prtd6r4g3doxcvbrd75ssgx5":["jamesnoblesv2","James Nobles "],
"oxo7tf3zufdczpvhsyyhw73x":["jamesrobertnoblin","Rob Noblin"],
"6mfznb75fph6lxrnxgahbxw7":["jbdschool","Willie Nobody"],
"rkckysbptxn225wtgaxmnwl5":["jjadamson","J.J. Adamson (nobody calls me that)"],
"eh72tamvki44ue2szgtwg6v7":["jnobel","Johannes (Jan) Nobel"],
"uy2jxz4o43whdsyptqbnaee5":["jnobles","Jenna Nobles"],
"65ry5rl32ywuybwsgkx22rux":["joshnoble","Josh Noble"],
"6ttzphcjdoc6p5ho353puaue":["jo3gf","Nobe"],
"6ecjdv7ybtlzgqz6j4ew3ic2":["jslipchi","nobody asked, but"],
"sf7cseboz7dvlznsj4zgkksz":["jstyles17","Nobby"],
"citbkq4oly7jevue6n6ff33c":["juniornobre","Júnior Nobre"],
"r67ynw7zecanrbauyo47hxeb":["justmefolks","A nobody "],
"zoj2tochn2pffdwy4rebefet":["justkrosh","Nobody "],
"xji6isdboukh7owovhjr2yxr":["kale","Kyle Noble"],
"5kxkyrxce32aolrnax77ovv7":["katster","an internet nobody"],
"hfjb3iwmcfj4zaoaqdpgho32":["katienoble241","Katie Noble"],
"wbyqzpykorllwoyn4qwbjwik":["kennynobleart","Kenny Noble "],
"iuewfimuwrlenisfl244ywvr":["khalednobani","Khaled Nobani"],
"u37rdnyvpdlrfyk2nizz3t55":["kimberleynoble","Kimberley Noble"],
"nqjap5cyt3mttv4rodeek5bk":["kingnobu","Nobu"],
"ifbw7vptd6odm57hjvtjamkh":["kiwyko","Nobody "],
"wrpcyzrbsocchfeabi5wmsms":["knobohara","kNOB🎨O'Hara （ノブ🐦オハラ"],
"fwyxsjxfxahmiok6wqlwuf23":["kxllswxtch","Nobody"],
"m72hdgenyc2qwse42pcu2fbq":["laurus-nobilis","Bae Laurel"],
"tkiepovp4m67i3j5ygsfb6sl":["lesbihonesty","Nicole 🌹 Eva Noblezada stan"],
"rhicnfzlbsrzwjshky7alrqs":["leobraganobre","Leonardo Braga Nobre"],
"sia37u22pue4bp3mspgskupj":["lespin","Lisette Espín-Noboa"],
"62s6q3g7lzc4ynb7mfqzgqqt":["lewdnobu","nobu"],
"sxoob7jeujjxhqqjv3o5j2z3":["lenoble","Maarten le Noble "],
"yvd7bq3jf34bdmohgsllngq7":["literalnobody","Literal Nobody"],
"dcv55gnuob44b5tj7e3gsanq":["lium","gás nobre"],
"g63rueeit3kvdkpr3shk23jg":["lisakennedy","Lisa Noble Kennedy "],
"2s4yiaf23eujcpvt26ydffze":["livinginmovie","nobody"],
"mru4d7wtypnbkuxz56t5ygzm":["louobedlam.com","Lou Noble"],
"wqq6way3jsxpopjatuwpozjp":["logannobleauthor","Logan Noble"],
"snxocoq4pvcjinuecldgbuv7":["logannobre","Logan Nobre "],
"ppl6v5jtvrsviswtvogcgfwv":["lunarnobis","Lunar_Nobis🔞"],
"k4lktywmjipjm3ejf6xpa6zb":["lucascecil","Nobody No-One"],
"qgp4nykfifk46mfskr7m4iln":["lynenobre","Aline Nobre "],
"htdqtcwt2cjgrfwpsrtnvkvp":["malcolmjnoble","Malcolm Noble"],
"qld526qdomvoukssbx5f2wf6":["matheusnobre","Matheus Nobre"],
"whdrpfrzaeskiegt24td6llr":["marknoble","Mark Noble"],
"luwyzjygkjsb4regzi62kfp7":["marctnobleman","Marc Tyler Nobleman"],
"z6xjykqt5cckrj5xf7of2uzi":["marcusnoble","Marcus Noble"],
"iytqxjkg7scxf2o7jlcllvtq":["machinist70","Ken Nobbe"],
"xiw2e3cwko22kczsdfihztyh":["masa-nobu","Masa-nobu "],
"gkkoht4l2lcsngaw72jjuyh3":["mandalorenoble","Noble Six"],
"yopr7htghx7onbdj7zxuw3yn":["mdno","Matthew Noble-Olson"],
"r4py4ova3sdssa4y3nf5cby7":["menthaepiperitae","P.Mue Nobody "],
"2wpcvc7wdrhgaqntgeglq2xl":["mikenoble","Mike Noble"],
"35lktqpeh5klf77fjululglh":["mitchnobis","Mitchell Nobis "],
"djnhkjxfqd63zaemqz7r456o":["mmn","Mark Noble"],
"ey6omgd53j5pyih2uqiqbyzy":["mopple","nobody"],
"4ip2yptn53qpmcvwu6xzc5te":["mocchi-nobunari","もっち。"],
"x4nfaue4yx4y2j4zr3qssx4z":["monispage","Monika.Nobis"],
"4crfqlwgy7xf7xdh4cocts2u":["mohammadnobakht","Mohammad Nobakht"],
"dyhjiedsmgwzt6z22ft22pxq":["morgananobilitas","Morgana Nobilias"],
"hnrumluae767f2d5kjblwxkl":["mrlemon","NOBODY MOVE THERE'S BLOOD ON THE FLOOR"],
"gjltlx2wmilzsb6u4xueo6ce":"mr-nobody",
"xrudsdhiyitk67d2hyrvqs66":["mrnobodyxyz","Mr. Nobody"],
"rw5asfvyqgocjdj73tb7jkla":["mrnobodyvt","MrNobodyVT"],
"hsjc7ygtulhh24wwufmoisui":["multiflora","nobara"],
"fkdwfe6ntr5lhz6m2gtbgmaz":["mutneoi","nobodie"],
"4lkid7zsj665u454z7ecsvdc":["mundymorn","Danny Noble"],
"6pkb43clcoih6vrbea647uql":["myllaindrama","Lady Nobody "],
"mak2443yocicaa2vtzsdll5l":["n0kada","Nobuyoshi ☀️ Nakada"],
"x3lcjpqpmzeuxsibgesl6ohb":["n12a","廣田伸彦 / Nobuhiko Hirota"],
"ciogwv6wp2hqbyiqpkwzw3cg":["n2beat","Nobuyoshi Nagashima"],
"tcih4hkrkmmuwkwmgbfhddi5":["nakchios","✨CEO of Maou Nobbu✨@ siete simping hours"],
"onhgeqdoytond474bh34ij5a":["naynobrega","Nay Nobrega"],
"7keeitrk3dupmyogglknyb5m":["nathanielnoble","Nathaniel Noble"],
"2opwhutdcbzripdcsh7h5nrd":["nadinenobile","Nadine Nobile"],
"piuzuwvyxnoity32x7cilw77":["nbsw","nobuhikosawai"],
"a7la5fn2uhjyiy66xp2plt4s":["nble","noble"],
"csuufllgyq4zymvvu2hj7uom":["nbcs","Nobody Cares"],
"gl6j5zu4ku34owi6ny54rx6u":["neonnoble","Neon Noble"],
"f4g37wpx32n3vrrm5gvb6pxr":["nicolas.grumpycoder.net","Nicolas Noble"],
"feppmdraio5es77bxzewxrkx":["nicknobody","Dr nick nobody"],
"y5rpvive3yhqfmycfcg7jkne":["nicolanoble","Nicola Noble"],
"oog4vluczitv5absw5242uqq":["nicesmile","Nobody"],
"bbkznp2g75upplm6hgumetjo":["nilo-nobre","Nilo Nobre "],
"wb2ngcdx34dubxwvaeguzfub":["nico-nobody","Nico"],
"3wsti3ueoutbjdqpya5ey52s":["nickisnoble","Nick Noble"],
"ip3ih5qglagciinqrezdqhkb":["nicolanobile","Nicola Nobile"],
"x2sceypscnhe3kvbroq3yq3s":["nlannuities","NobleLowndesAnnuities"],
"2nslephdz3gnfh6n25dxeqid":["nobleqali.rznwa.com","Q. Anthony Ali"],
"4lkimredrza624fdl3ghzrea":["nobutron","Nobutron"],
"4mc5vkbwgctgypl2khvd26km":["nobodyowens","Bod"],
"4weyi6u32khjrijhgmfdplei":["nobuhojimichaan.com","nobu 🟣🟩⚫️⬜️ '"],
"627ivsjwwhhuw6sgddz2msbk":["noborderline","Heather Ross"],
"7gsl2444we3lnp2aw7ij6dno":["nobodycarespj","🐬 Unaffordable Black-Pill Prescription PJ"],
"7krz3r43v5pzshbqoq2ayfhn":["nobody1300","Jeff 🏳️‍🌈🥌"],
"7vrcyetzhiyc6i6x2dqcyhqw":["nobpeck","Librarian to The Man"],
"7w3qo772y6f3cndhyxocof2l":["nobr","nobr"],
"a6pswlwbhhsflmamyrwgocrl":["nobogasawara","Nob Ogasawara"],
"awp2i7gqsqmf7wsztcee2ea6":["noboredom","Kein Bohrturm"],
"biel4simayesab6tnaguhcjb":["nobodynocrime","Bruno (60/180 for Lyney)"],
"bnkap334oy4ghbznzedxove5":["nobodycares","nobodycares"],
"bw6hnrvv3noht2zr7swd6r7q":["nobleclonetrooper","NobleCT"],
"cg5am4npoa63dqns7ekdqowq":["nobunny","americas most eaten"],
"danwjbjb3hg3jah4jn5ao6q6":["nobreceara","Nobre"],
"e323nzr5tfc7qjs5ymyufz6f":["nobumipup","Nobumi Pup"],
"eralrpepyk4luvvfblfdk2kv":["nobodybut","I have no idea 🏳️‍🌈"],
"f6qmw6k5y7l72k7nzibjez76":["nobumi","Nobumi"],
"fiklr6sf3wrqsegvhjv2v3zz":["nobodyimportant","Just nobody"],
"fxjwzpf46ucqhas4tt4tdemj":["nobzilla","Chaos Muppet"],
"i56o524gdey4gabr5wdaiv3c":["noblekind92","Paresh Maharaj "],
"iace4iicv2lvctxs42vxus4c":["nobodyishere","Nobody "],
"jxdqvqart2qr6eazlgrmtauo":["nobitheram","🐏Nobi The Ram🐏"],
"khn6nbv2e5am6kwoomsjamlt":["nobadnoel","Noel is a man's name"],
"m7d4gwxipyzybf7iozxxochi":["nobody-indepth","Nobody"],
"miee6w4rirhljrbrzrjatfsd":["nobilis","Nobilis Reed"],
"ndnrdvq67kglelgf7v4zj5zk":["nobody","nobody"],
"njcv3zbc6euydz2nlej2f7lb":["noblet","Patrick A. Noblet"],
"nkakrplwelbytre3qme6p4c7":["nocturnaleru","Oda Nobunyanga"],
"nq4qpqgv5sc65q4h4yxzd5j5":["nobleingram","Noble Ingram"],
"ozd2gjmqjwwwyav6vh2wbgnv":["nobleprize","Noble Prize in Sarcasm"],
"p5fb65ahghhgagurljcgwgmk":["nobetcialkolik","Serdar"],
"phyzch7srlkdc2zc55ye4hri":["nobby1138","Neil 🇨🇦"],
"pyhxbcecsajan5rvlcswqnrz":["nobooks","never read a book"],
"rk4mx2pjwyrg3myr26dyvfni":["nobu-k","Nobuyuki Kubota "],
"rlg457tjo4hxqal7gojoqpqd":["nobodykn0ws","uηкηØωη"],
"rp6k2sbxokoawdec5rd4w2yl":["nobrysta","Noah, hymnbo appreciator"],
"s3mnyxzc6zftrbzwa23krv44":["nobswolf","Nobs Wolf ♂🇩🇪🐺🇪🇺📡🏳️‍🌈 📯"],
"se7dwvn6emnft57jdq5diwc6":"noblehunter",
"t54w5ywr6odfhc46funa2vhb":["nobylu","Nobylu 🌵 Alo Curio VT"],
"tut6drxajn2z734tdts5hqex":["nobubu","のぶぶ"],
"u3biw7gyoiu3qihejng3ufr5":["nobkodera","小寺信良"],
"u6q2zoamzgwxbuxwogcihgkf":["nobuking","NOBUKING(Shiba)"],
"uv5u5lm3ouqczxvjyfxep327":["nobirdstofly","nobirdstofly"],
"vgr2ugrrpcsyssbv2skcw3nz":["nobonzo","no bonzo"],
"vlkqnwyshzxq6wyzgfyl4t4k":["nobsato.com","Nobuya Sato"],
"vt7nddttj45hp5phtjgvhb6s":["nobu","Nobu"],
"xkn7hahdmwxmxa3vhmr3xuvo":["nobita","O. C. ホイ"],
"xxctyk6c74ldzwlnxc67jl7m":["nobody-see-me","Mr. Nobody™"],
"ybhtjnvogdc5jyd6czswy4i2":["nobo","nobo"],
"ysnvhhc7h67wcaqmwrtizdwu":["nobilor","Nobilor"],
"lyuaynwada3dvhsrscduwayv":"nobru",
"wiyvjmbzbzlrszy4hvr54ncr":["noborunrun","noborunrun👀"],
"qmyz36plt7ebjz6rbat5qhhr":["nobi","Nobi — Nobuyuki Hayashi/林信行"],
"pmgg5a7loh4lewyklojwnf7i":["noblessefemina","noblessefemina"],
"67cljy4uyntl2cynowk6pd7v":["nobuakiyama","Nobu Akiyama"],
"feabadzgvhkye2wd6z7i7fc5":["nobulb.com","Mike Greenberg"],
"l3wgxiaydfneot4wjbhyp6bb":["noble","Noble Gallery"],
"ww5aoob2jjsxiz77zywr3kwb":["nobles.page","noble"],
"it5wr4bwdpxv4chpjdfrpoqs":"nobodyu",
"5kuvopak43zeugv6szx4w5d2":["nob","のぶ（ものくろ）"],
"u5et4atfmyjzskzqeh5bi7x2":["nobatteries","Meg"],
"r6545to56efspmfpouq2zvbo":["nobodyclothing","nobody"],
"6nvp6b3rba6o3zx6yrdftw6n":["noby","Noble "],
"7gagbmcf4d7fv4nrr6gvr75u":["noblesquashy","Squashy | VR "],
"zk5x2z3pk2b5nipar6fqapmu":"nobodyman",
"rzeuoxxs3f767ekbdvgu5rad":["nobueno","Chris Bueno"],
"f4whblgjlc2ndn2fxbaeh7np":"nobitex",
"diinbhceldjcw3mkkmc4avsa":["nobonobo","nobonobo"],
"6edlwxtnzqejshgtfsis6cw4":"nobuyan",
"gvbykceiqiz2foi4o3nzr7qh":"nobleand",
"pfbd7tosplo7w2xvoo2cljpw":"noblehappiness",
"r5tdvzloiex53qohjcfwxf4t":["no-body","Nobody"],
"fdgmepxmhffl6mujemsnz66l":["nobe","nobe"],
"4nf6xan5ehr7lq7b2jgcdqgy":"noblefrankie",
"xfmedpobrj73b4e4vw45wxks":["nobey","NoBey"],
"daix546kkslae3qbpme3m5tm":"nobutactually",
"xhuscwmdeurjzix77kcvvze3":["nobuoka","nobuoka"],
"3yj5hgpifhb4bea5zlznljde":"nobahar",
"7liwzus6v2pvrmfbyvltnonx":["nobodey","Matt Moore"],
"imfdyryxdjlc5bcjztlkvsvd":["nobuo","のぶ@ショート動画強い"],
"hem3fvafgvwfgai46w247miz":["nondesign","nobuko yamaoka : non design"],
"7txuxyfcothfdv2frk3vsu2a":["nobaveh","Nima Nobaveh"],
"nrfnqxfhqdrlepjhu53zo2jm":["nobs57","nobs57move "],
"5mzf2mu5fdhi2bolpejetyzy":["nobs","Nobs"],
"xwffnp3pspl5oki4fk6vxtfk":"nobody2knows",
"mybvxn7mkxvxpaz5q3x6miwl":["nobakimoto","Noboru Akimoto"],
"z7dsxl6dztz35pbbatjbbn2f":"nobu1024",
"ceoa6x6ahe7xlsygcgipb56y":["nobleexperiment","Al"],
"zn6s3gfzoulhnuwsosjik77y":"nobara",
"3s4uxmiimhsa7nniskm2cqus":["nobebocafe","nobebocafe "],
"qpvamirpd4baamgrcyti3ung":"nobleox",
"ch322pyw4yufq4qeiu54rxlc":"nobodyuknow99",
"c7beelk5tjc5ilfnvyysq2tl":["nobussan3","無機物産"],
"6edw642n7wy72uuqe2n4256x":["noblestabbings","Loaf Jouster"],
"yxu5rfkteafnrrp4p4kxwisr":["nobody1010","nobody"],
"sbejghxkeqyp2am22f5sjpg7":["nobodyfaster","guilherme "],
"fc5xmanajt3cgv3pmuywxmgb":["nobells","no bells"],
"4ialrpa2vx5xrhxe7zuoibtc":["nobikko","のびのび"],
"uemolx2pcruko46q6fo5ldek":"nobbie5884",
"zdr7dqnso2cuhiql7sfwme3b":["nobomommy","ethereal dynamite / ire [of the] tidal hymen"],
"h3eawjwksaerfwkm2s5lmdq5":["nobody24601","이사람"],
"gi7254w3xu3ktyq72yug4oxl":["nob-of-joytoy","nob of joytoy. ◢￨⁴⁶"],
"5hkk2pevzj4xszylmxymq6n6":["nobodybeatsthebriz","Thomas Brennan"],
"ivfj7c356my3el4tg5urkk4r":["nobreconde","NobreConde"],
"jhejrnqmjgnpcephq2dbq3aq":["nobusat","のぶさっと"],
"cbdgzdykcswgabo22keha3jh":["noblinkyblinky","A.J. Murray"],
"dnwsvmqergt3inykqonaro5y":"nobody696",
"ggkczhp7qpyyyiiiey3duimj":["nobodymrn","استثنای منقطع"],
"cknjovwmo562mfmbilvkfwl6":["nobu-ohta","Nobuyuki Ohta"],
"yoiqr7y4sugeebfui2julwdn":["nobara303","mayuge303"],
"s63minyygch5zaeraqaq75oj":"nobleloaf",
"rz5mxgobwzycj4ohbekautzl":["nobadanuki","狸"],
"kjt2e33nwvuhxczfz6vmrltu":["nobleruin","nobleruin"],
"rgkjmbdczd3f3zffclvd6hll":["noboku","Nobuyuki OKUMURA"],
"c3z3lmgh6fjhu6e7xmjnpsmr":"nobu425",
"4hedih3kaw2yodrgdkl5z3nm":["nobtaka","Nob Nukui"],
"vb5tjpwakythb32qek4lzjop":["nobrandjenn","NoBrandJenn"],
"ysixr2mnmca3cvoeqb2dse2o":["nobuttstuff","nobuttstuff"],
"vlqj2wflm6fptshr4z5hvtsv":["nobriggity","☠️ hannah briggs ☠️"],
"wqhh344vq76cx2v623t64ynv":["nobre","Nobs"],
"fx6g2s7skpuxjxqdvb7l37hp":["nobikun","つ。"],
"ejfmyphq7ei45l4ijo77bp7v":"noblej",
"flisbecg7ifaod22seunrdvc":["nobrefilm","Nicole Nobre"],
"c7bpgmt2r64auhu3cyv7poh5":["nobuyy","Nobu-YY"],
"bvn3xn4iopnzo5yvc2q7sddz":["nobodygrl","Shana"],
"6bdjfatgjjjzrk6lw63ad25z":"nobodysignificant",
"qhuvmarlrhdmy57r7gxg2pkp":"noboddy",
"sa3fvas2dugchv7wbn2jxi6e":"nobody0",
"ftjnkgbsv3ki6o5ik74bu4y6":["nobodyinparticular","horde captain dipshit"],
"x7iza33eveplqh6mb7taihn7":"nobu65535",
"bke66kmzuesx735jszjfqxpk":["nobalisk","NOBA"],
"3tsgpjrmuuktczzhb347s6jy":["nobrakes","Alex"],
"j43hhkbcx5ifelpfffoh4gy3":["nobel","NOBEL"],
"howlmqmh4ef3psf5chgn2e57":["nobiinu","nobiinu_"],
"iaak44wkq7rgbllz4wpdunmo":["nobptl","Nobuaki Kadotani"],
"q4rqoxx3t6d4vrvxlntvrq5y":"noba",
"q27fsj7hwhteva32epjevnc6":["nobunaga","ノブナガ"],
"72qpiyynghcxkuvklojeedzd":"nobodysuspects",
"zipmzhtjis73xusy4gpbiezu":"nobodaddy",
"swb4s7xkj7nnhvc2ys2gepch":["nobody-shapes","Nobody"],
"irzof7zpcz7oykx3seguk5mg":["nobuka","nobuka"],
"u73gw5pezmthfg7cj7qjl2df":["nobelessepod","Nobelesse Oblige"],
"rwopf7cxy4nixcjyhf64ocmq":["nob6969","jillpilled"],
"vuwjh7tqesgfx7y7hovd6wfa":["nobu.ltd","nobyy ⚡"],
"w4nohkyef3vtiyxkujdxvtcn":["nobitinha","Dom Perignon sem lacre"],
"f46ruhyuliwgpluk35bvg6xf":["nobettafeta","Mike Profeta"],
"xaovoui44r3v6dsffmqwurpz":["noboners","noboners"],
"komrrcqrp24shne5ovnmkgaa":["nobuyukithecat","Nobuyuki"],
"zqmnlgjokltgbemmkws37nkp":["nobrejuanpaleoart","Juan Nobre "],
"7mvghp4lm3qfwvy7ec3abk2z":["nobiscotti","Biscotti🇪🇺🇵🇹🇺🇦🇽🇰🚩🇵🇸"],
"owfsxs2fckhlcvfccvonl5x5":["nobelance","Noble Lance"],
"uot3bb5wd2l2nbiwohymi6x3":["nobattery0","이노"],
"ake44heba3nl2k4zfycpajbg":["nobkz","Nobkz"],
"3mio62frdflei4btyicyv7ot":"nob0dy",
"vrxlvzagkbpc4fo343e752ar":["nobleline","Nobleline"],
"axzc2w4dwc6hljyet6xqpx4v":["nobidil","failing better . . ."],
"epcag4wofblt5rgopx37vbfk":["nobutanaka","NobuTanaka"],
"z3lmzuvso3hhfmh7cbca37ad":"nobodypn2",
"g745su2ib7hr2vui2iw4od2w":["nobory","nobory"],
"m7ejsmkbbnxjdpiczgofbynj":"nobrain",
"u5fvmnojbulza5jrnbfoxm5o":"nobodycool1037",
"djo7j4xettkribcvnysy4zmy":["nobod13884","Carole M."],
"nkx5bwgii7nl6hmbse6vn4di":["nobrejoao","João "],
"cqfdoeiqva3vyzh6o5xofyea":["nobleprimado","Niya | Noble 🦍"],
"mkgfb5vqjmyj7uzdjbkupp2q":["noblefern","emily?! "],
"kcftckcz37ygtjuuoq4t4icq":["nobuw","のんだぶ"],
"5y5klnxhmhhd7i6sekhsdeyg":["noblerorick","Kate Rorick"],
"qf6pdssqueevzhrrgjw6gi4r":"nobonus",
"3jbgw3irgewm34lwo47yydt7":"nobynoby",
"pa7ihpdsbgbnadjmg5cu6xln":["nobukatsu.jp","nobu"],
"xp33vd3ftxlxk46gaflp72xm":"nobu3",
"5hmh4v63h6abvdvczlbq55lc":["nobodyluvsu7","❤️🖤Nobody69🖤❤️"],
"i5epbinwmo7y2do7ndqk2x7d":["noblecrumpet","Noblecrumpet"],
"jbas5xrijefqcy3cfyldabig":["non-matsu","Nobu Matsu"],
"jd2g3gcqo7chodcijfuyre7l":"nobiring",
"t2z3bziey7rtwbuyrnqsnzgl":["noblita","_noblita"],
"sq7zopl64owizttovjo4pbr2":["nobodyhome","Chris "],
"gfhyqui6axpox57d3ozrohxf":["nobamaki","gio"],
"6icrqlyvyxbvjqpz4d4lqaz3":["noblesolaire","Valor"],
"c2nupdn5klbiaq5nsshbfaed":["nobleless","김 노블"],
"kv2pknvs5fyatsdhnwhwqjkb":["nobodyy","Nobody"],
"iyr3baofdd5kddiorkzty2dh":"nobsip",
"liwv6t55davdqr7ffnvllgj5":"nobl9",
"nbpyvwb5x2zllzle25yazet2":["nobsallowed","Lettia"],
"d4oalgkpxror3pirnlwc7yhu":"noblueberries",
"t5tkas7iky56nlyso4xggjro":["noblemannick","NoblemanNick | Producer & Designer"],
"cvembzgawzo7nfzi6ssszk5a":"nobua",
"ycvqay243nnpvalsa4edq7vu":"nobodyshome",
"p2gpyknmythw3vte7s3rk5ec":["nobb","のぶくん"],
"4lqch5mxnmddodbad5lfl5j6":"nobunobu",
"nmbznwpzsiev6u63aywidsaf":["nobuaky","Nobuaky DX"],
"fuafhstmunipv4al2iwwy5mr":["nobedbugsatdoral","Quintesson Lawyer"],
"opn5lc24aa5q53dckx44isui":["nobleillustrator","Noble"],
"td7gpnh4q32wrltp4x5xc2en":["nobodyknows","Nobody Knows"],
"cts7cp6codavkzldbrzmh7uf":["nobutreally","아니근데진짜"],
"picuqec5npxvkecdh54qchwj":["noblessenox","Fagundes "],
"io7notr757nwqax7cn5ioz33":["noblestea","Noblestea"],
"ucvokduonhv3jnf7rxwuamgo":["noblrnate","Noble Nate"],
"7l4dsettv3q6ldyl2mcsgfcj":["noblinnea","linnéa "],
"vtqbpocvey666cywhpk3jn6j":["nobuell","nobuell"],
"ze2z7udrr5enq6lt4judmlau":"nobody33760",
"ykmi5fkrj25iz56c3e3dpk6a":["noblejanobii","NobleJanobii"],
"dmuexeb2yohytsrahwyvj6o5":["nobeena","노베"],
"qxhryesy7orsmfcit4n72avw":"nobfox",
"b7ip3eitggw7rkt7ldre2xue":["nobodyis","(sandy) kenny g"],
"3amijazubihdtbortvaq5dzu":["nobyrne","Nicole O’Byrne "],
"z7g5iakptlqte6pbao3y7oha":["nobodycam","Nobodycam"],
"4sfjho43txquj2ehmgo4i2a4":["nobread","Nobread"],
"uyosrd3bjr6fj2wwe3a354us":"nobondo",
"hnoodes7vyyygybl6kzekg3f":["not-nobel","Not Nobel "],
"sr2k6dmqav6liq3assg3wiba":["nobodybeast","NobodyBeast"],
"ecdq2lltfzotmfo26uqs2nec":"noble1557",
"fk4e7nvt6rauw2oja3heycro":"noblemule",
"gu75bn6nyyne77ukb5l7j3eb":"nobodylikescris",
"uv7jwnzxipaid6pykntq7mqf":["noblebrew","Noble Brew"],
"icz2hcuy2vovnviy3buuzeve":["nobunagashi","Manu"],
"ka42tjjs3cus2i6htvlsukf6":["noblewolfa","NobleWolfa"],
"uklhcmdv7tmzmywcc26spyn7":["nobby81","obuno kiraa"],
"xqywgvar4sqnbxxgzv4hb2gg":["nobliqus","Nobliqus - John Coughlan"],
"4vonh6ypqnveylmd3cpztza7":["nobodywantsthispod","Nobody Wants This"],
"3eoav3d7bev33jl7vues7xuy":["novaria","Nobaaa"],
"g6hgujaul2tszww353hoinmm":["noboogie","Boogie"],
"67sb5yl5dv6ipfruco7z2a5k":["nobulogna","Shiki "],
"jr4ibd3smmchafogherl6qwx":["nobodyshouse","Nobody's House"],
"ajodvsvzu4ffuuzzb243bv7m":"nobu1969jp",
"q76emluaho2rqvxe3ktegdtl":"nobfar",
"2b53r46zgytfb2fikjysfh4y":"nobble",
"ffthwqxbqz4s7n6lhhirx5c3":"nobodiesopinion",
"dzwpwnedqavtpbas63yahrep":["nobtetsujin","NobTetsujin"],
"vjq22rlyhizltnzxvizdmnpw":["nobbynobody","NobbyNobody"],
"io7in3yjldlnshvfabvcns2e":"nobby",
"7wzgxwxr5ss7ewaoiiytjwd6":["nobsun","Nobuo Yamashita"],
"67z7v353xhr65mxa5ecwnumh":["nobusuke","Nobusuke"],
"qtntyqj2sjt6r4cofxhfwsce":["nobuofox","Nobuo Fox"],
"5fi2in5tzkyofxjalvzfoq4e":["noblelynn","Noble"],
"4uxyi7ria523tp7pjmkp72yg":"nobilega",
"jdmit2j2q3jqhzqctsatfnh4":["noboruarata","NoboruArata"],
"yoqvzyhmibuu2d6zybu6cxnc":"nobu-y",
"h63x75hzndrd7n7lpejapbf3":["nobukatsu","nobu"],
"c5yxqce5rqunagohfxjwrsv3":["nobelgas","Jimmy Dunne"],
"vytd5ucxjjoo7ysgkvlzgzzo":["nobuzeus","Nobuzeus"],
"5xqvogrleqtjirzqacuf5tms":"nobody1923",
"qi6x2b6s5gkvmdahewem57nb":["nobletrail","Xyloid Inch"],
"jopniifyy4kmeawg6e6mltgf":["nobrieny","Nancy O’Brien"],
"53phuxllyszup44rmacywmqk":"nobanora",
"x54tbadxa6ydl6zelqloukr3":"noblefox",
"zb7dxzsipph2j6itlkydqqyj":"nobbyno1",
"nbszyam2eu4xe4r2etu4jkyj":["nobbitt","nobbitt"],
"aremhaqpiergvyrb2ekh3yjl":["nober","Nick Ober"],
"6jdsceae535e3piazvxvhrwv":"nobytes",
"gwl2ntqupdkvwmmf7rgk4lj3":"nobluffu",
"46hxz25vv6zmeymup7oyyn2x":"nobodysgonnaknow",
"x3ltynhrh3zsmpluwgftzzte":"noblelawyer",
"3z64v7ilkxwykimlitcp44ih":"nobokko",
"obhlapaltdece44aans7hptd":"nobuend",
"sgfq5u32ttspkyunmijlocmj":["noblederg","Noble"],
"7hhralsvmsbgx33zzw3ooc7o":"nobitanobi",
"xkiqbq2mckkpwigwutlaf6qx":["nobleslurs","Ross Bullen"],
"l5e3mddsltwcdewklux625go":"nobal",
"uaikyj2socfwgu5agwjeq3ce":["nobody1","Nobody 1"],
"mtq6f5p2vjjfng6ljrl2ihdk":["noblewolfheart","Noble Wolfheart"],
"vzfotzcaveemli763yi76q5w":"nobuy",
"o2lzbd3zh4qh74p5dsa335da":["notsonoble","NotSoNoble"],
"ajgqpn5z6focqdgfcd6pouq6":"nobleknits2",
"6646wlibsdcegqoh7ikx6k33":"noblewookie",
"5n5c6gldzl4ozckvkymhtovo":["nobodyofcrypto","Bod"],
"r2kyfgavikzkrh6u4v3u5kh6":["noblealice","alice 🏳️‍🌈"],
"6v6vkvqqkdud55ng6fcgztmc":["noblenelly","Nelson "],
"73tbaicgxvqekfjsotmqb6n6":"nobuttsnoglory",
"wfuho5faoxfffd23cm42bntv":"nobe0716",
"q5c7uhzag4aokoubymegrbea":["noblemansrose","Dominic Zullo"],
"kjnxq5x55nlywn2p6qhybzez":"noblefieldprince",
"mubrbewjaedvtmkkvmic22wn":"noblewolf161",
"uqs56a6c7me6zb6jka3qw6dz":["nobunagashinbo","新保信長／南信長"],
"26bntbxrfen5jg64cqbmsgyh":"nobody00021",
"qgbipt772tqpgmunu76k774w":["nobody1312","Dee Pea"],
"5ncun5xpwcwdfk26dlyamfxa":["nobodysholm","Peter Holm"],
"dmqwtfvrfdltwe72j5sg3ubu":"nobusinesshere",
"hbcb3jmf52s2hxck2qnjqa7o":["nobodyever","Nobody_Ever"],
"yuaffz4zltrtkywl2rwhp5xc":"nobuyukishikano",
"adoolw2kqhelzomy7liqc5jv":["nobu0","ﾀﾍﾞﾀﾐっのぶお"],
"mse2qnqa66umep4jke5n7lcp":["nobio","m b s"],
"4gc2e7yhxccchv3j5tw44jz4":"nobody11",
"pofezjutfqz6ucmmgpz5igep":["nobasaran","Başar Başaran"],
"gepdccpw4jmbdxr5nnzb52uw":["nobug","Nobug"],
"qf5rtt4qmyfmegvjz4dv7m6g":["nobutrobot","No But Robot"],
"buzzeobbo22do66cvyeyo56x":"noblepath",
"w3rifofnn3ynw7h7y4d6liu5":"nobiruusagi",
"inzj5lpto7mbtmssryz4boic":["nobyl","Room 4D"],
"pynnkrk7plxwqvzpw5iqgrln":["nobodyknows44","μ"],
"vksrk45n7lczjz76gtbgydmx":["noble1","Noble_1"],
"waal3v73coulrcfzt3onf3yp":"nobitingmyarm",
"rudezzz62gebstiglae4lhe6":["nobody147","Nobody147 🔞"],
"zhxlvwnrlfup6szaixdoaaki":["noblerenegade","Noble"],
"jpeyftra3l5enelc2jfhxzr5":["nobracommander","PunkyTeuchter"],
"tdcmp6j2lbzdnq3blfycwm2w":["nobullsongs","Wataru"],
"vcfl7bn652ybd4sle2pftolb":["nobbydenobbes","Nobby"],
"iyyrmb4r3h6hmhuieu3k62z2":["noba7lico","野花リコ🍓"],
"6zkidvdyqhjlbdet22szd7er":["noblelavender","Noble Lavender"],
"hxbb5fbe7r7uwqvppmxoh6sb":["nobhal","信春"],
"l2hrezllmhwb65inziuy4lyb":["nobinobiko","のび"],
"72ufoymvnp5l4uzj45sc74ra":"nobizaemon",
"2vwy5fcqrjjqjgftmericdsw":["nobukanata","nb"],
"rys4xsgxyjp4shptxsz6yojh":["noboriis","のぼり"],
"4bpmb5estx7of5yrggyr7geb":["noble1236","Noble the Mechanic"],
"7a45hhdcq7u7w5ouben24ohn":["nobebahon","nobebahon"],
"lwz7435zjboueofglofz52ah":["nobodysparadise","NobodysParadise"],
"qkmjwo7yzfmno2zeq24ifnle":["nobugian","NobuGian"],
"krkiazkvassuzb5omj6dobsn":["nobodykid","Nobodykid"],
"ikczu5gpbnb726mreq5yhx7p":["nobayern","🥦NoBayern🅴🆇🆃🆁🅴🅼🚲🇵🇸"],
"n6f562hfzllzeouszkrjj5ci":"nobodywazhere",
"ubvnmiezm6sq7ggrgvfwudxu":["nobodysmith","Matthieu Ruard"],
"j3mhmxumthzqxodhewniezjr":"nobodyliveshere",
"t6yz3mkyhfppsmtmwe6mrqfq":"nobjustryan",
"7nqo6jjfiyzysz3liov2462t":["nobodyaddams","Nobody"],
"osroanpqkj5wdcxw37r54okn":["nobinya","냐냑"],
"tav3hx2p7heqimob6gqux4ci":["noblebalor","Noble 🏳️‍⚧️"],
"4gx3u4dlpkwstpqbtnx2ilgi":["nobutan","Nobutan"],
"lkgh5lf3ehueegavnmftqfli":["nobahs","노바"],
"dlf3zec5flpu6c3ennjzrnd3":["nobu14","노부"],
"inqayvnayukfzhbqk22kwgx6":["nobunny5","Kukkii กุ๊กกี้ 🐰| Tryna write"],
"e465y3c7tedjzfriukpqldpy":["noimportant","Nobody"],
"xdg6lzmq4fqtyi4bgvlxn5nm":"nobodyhearsme",
"gisugem6kcp4p7xxrfxjbqwv":["nobtwid","nob"],
"c3dq7cp5d4nzebb5x5t4gplz":["noblessejess","noblesse_jess"],
"tbodvushpfpswrdg263vlqlu":["nobert","no"],
"2vqwbgqer7x37uh65laflkkl":"nobodyisherenow",
"44w5oqfisaoabbj5neyk5qd2":["nobutx","細谷伸之"],
"igwwc27rvb2736lg5glpo4k7":"nobuatkt",
"bmjmdibilmhuakw3vxnwaw4v":"nobodyofficial",
"uxzuxkao3ibdcsvlyc667gny":["noblejkn","Jason Noble"],
"gomevepy5zuad4rbh3yulldm":"nobnobson",
"edwsenmhiewedbvknqk2xf7y":["nobure","Nobure"],
"grzzwonunytmovlhhw2o32il":["nobodynowhere57","هیچکس هیچ کجا "],
"oau35mrw5bnqjrz545cwe6fe":["nobuwobu",".nobubu♥"],
"ot62jsllwsdqlzuefugmx5fs":["nobatshell","Nobat"],
"o47t6codosehcjzqgagcrukb":["nobbyknackerbag","Nobby Knackerbag"],
"nutcomsztkqpbapu6etxfoen":"nobuyuki",
"ks4kd6ubml7thkmr2kdflhhk":["noblezobs","Christina Zobel"],
"nrr3xdjfv3prj2wm7cio3xdl":"nobobloodwolf",
"ehmbhqbmeaumjwvieokytx5m":"nobuko",
"ymwo4js4z263ewi2gttzgpww":["noblemansdemon","Astara - Digital Artist🏳️‍🌈🏳️‍⚧️"],
"hz54owigqlpvq25ffoi6c4x3":"nobuhitotanaka",
"zotnk5ly2uysq6n7d4hhrfrn":["nobodyfunny","Herb"],
"cemddreqyn6tq3qno26sdyil":["nobody1oo","Imagine"],
"wugyhhjmipwl4c4rujnwq6z2":["nobu29831","nobu"],
"ig5fahnnrsi7rrtr3kvldodm":"nobananasuits",
"vksn4wfj43owqq43mx325ji3":["nobodi","Nobodi"],
"4q6zctmva5z2den6vi6l7f4e":["nobody24","Sleepy"],
"a2v2ly4wvtcdy5uhniaxrd5h":"nobuhiro",
"sncgjzfxzrv5n6btubvunokt":"nobazhang",
"zsgwqd7lkbroye7cnckc6g6j":"nobuseattle",
"mwjwcjfhlb25d5wwihduwchl":"nobugg",
"kvurxd5rcbww64tt5qplfxrz":["nob1e","M. M. Matzke"],
"gcackdhl2e6fsx5e6tpgq5ps":["nobletkhir","Легейда"],
"hrdyk3v2ev2ois464fgzpouz":["nobith","Nobith"],
"27ljn2qrpycphuxx3h5c2u3t":["nobodytriple","triple-a nobody "],
"mlew65bgdrec6lorcq7utcr7":"noblefire11",
"zikimthnqwrwgjlt6lzvz4fy":["nobodyreally","nobody really"],
"aoukddiy4ij2vs5sdkpf6xb7":"nobearing",
"cmhmifzl4s7w2zg4a2wjmvu5":["nobumoonwhisper","Nobu Moonwhisper 🔞"],
"43ekrxpoqezjqrqajvjefpso":"nobody01",
"mmpeyssjfq5fdmqewi77mbbf":"nobodi42",
"6zu75etja7dkta6wtxoufhwa":["nobcomics","Negative One Braincells"],
"ierp565zkb7n4krqyhkc5kdn":"noblerobot",
"73zk5x6i7p6o6j75jsep6fwp":"nobodywhatsoever",
"2buucbwa7h67dftntmtjcym6":["nobelhh","Nobel Schröder"],
"7uel6t5na56yd2rsa2soamze":["nobbi","Nobbi"],
"43e36htctdtthg2xjmloab4l":["nobbs.eu","Alex"],
"qgu2maipwvy6usut46tocsts":"nobodysnodal",
"ritlsuv6ayx3iup5k7llkkiz":["nobodyfromcgn","Niemand"],
"mrn7b2uwztv526sxtm7p27bp":"nobuyuki-rush",
"ionibq6wcjo5o5bhfv4zfe3j":["nobodysstraight","Nico"],
"7yf2ipjlevwecj4jjalmjjwd":["nobbse2710","ℕ𝕆𝔹𝔹𝕊𝔼 📯"],
"zjqsm6nnq224aclmvw6vl33d":"nobutaka",
"7dsfrwc546z2cwbglmhl5f5t":["nobarahanabusa","綿貫芳子"],
"4gfzjknwjl3uuj24ht7nfayi":"noblue",
"mtddiyetjan4w2p5xfwqghey":"nobodythanme",
"fqxju7m3xyglpf54xgvg2urs":["noblogforall","noblogforall"],
"2xqbpqbafq5erkskyvkykbxw":["noble-esme","Esme Noble { RP/Parody }"],
"ftxr56bvilxe34tn3mjdrjuq":["nobrainadded","A.B.CH."],
"qu6uxlee43h2bssbs6ezh5rm":["noborders","No Borders"],
"iv4smgdz3viv6bjotvjy466d":["nobodys","Nobody"],
"njlojcbopgqtfibrnlijdhno":["novpoecoco","Nobuko Yoshida"],
"n2tty4efumnfqobo7jueabja":["nobusato","Nobuhiko SATO"],
"vckfx2qpawncdd4i6nhh5cmf":["nobbytobby","Nobby"],
"i72voamtoko5ivi5h6le23sh":"nobbinatus",
"t56nwvje7nsdvpzv2nx6e72l":["nobunossu","🔞 Noßu? 🦊✨ | Trying my best"],
"6kjsbjahjnrd6l2x66c6zaud":["nobleheroine","NobleHeroine"],
"exwcnaka4coux4f2rnwxn2xi":["nobleshift","Shrub"],
"drmr6oajuznymx4hpqepd3o2":["noberius","noberius 🐏"],
"4kpqq43v7lnd2cx4toegchrk":"nobodyspecial",
"yb3kffumfescoxlwbtjlnpom":["nobupunk","nobu"],
"l4n65oss76cafkoe6y2kwtfp":"nobodycancool-com",
"girxxhhei54hhkxgqebq5q33":"nobodyfrm",
"wlexg7izusg52xsfdkcuxlgr":"nobsboiko",
"n3gr6csgvonvs4midzfd4nu2":["noblebydesign","Roxen Lucis"],
"wsen2fujdldcxhuahr6b4ufy":["noblesteedau","Noble Steed Games"],
"gg4fuy4w43wwfcb7d7ggmxvd":["noble3stix","Noble3stix"],
"tncf2um6oq63ov7bsntu2tji":"nobbu",
"sbwowurqmq5obxhkbjhfiq5u":"noblewolf1612",
"cjdjctuvwcwqmdm4vqxbte7e":["noblevic0896","Noble Vic Studios "],
"kv7ss3lwikengz5mh56gdolx":"nobodyneu",
"jz5bmryc6bf3qaqq3gstszfs":"nobodydreams",
"dnvazqjbxhi3be2wigwfpdqj":["noblemutual","Noble"],
"uaglgsu3hcxvj4eqdzxdghyd":["nobrain2day","J."],
"as7tbbhlkj2jrwxzirl6brxp":["noblealicia","Alicia"],
"zr2clmpno356si2zze4eghvz":["nobodyknowsathena","thena 🥭"],
"vyfiemgplyiwsdyt6dojadex":["nobarado","のばら堂"],
"o2y5en2bm4jxbyqh6o76d4wn":["nobukomiyairi","Nobuko Miyairi"],
"vklxwfuyzxwntmd4snmgprr3":["nobreza","Nobreza "],
"7j6v2w7hqifevormkn44rqvc":["nobu09","nobu09"],
"7tvelqa74nxdcxigfgsoxms6":"nobbyfox",
"sbhmzpamao2aa3yjbbrz6yt2":["novinobunaga","NoviNobunaga"],
"n5l3okmhz3bn7qahtcdrseml":"nobx",
"pxtgjaqojzden32jlql65oxf":["nobodytooimportant","🔞 Whatsit Toya 🔞"],
"q4yelbgrf7cs6guszas7h2br":["nobo0409","Shin-Kun"],
"v2tk4pyou3566bo5c6ejm5aw":["nobori","nobori"],
"l3cwkrsoswvdmpdwte7difrj":["nobeesnohoney","Fran Alvarez"],
"kt5e35o6y4gjytvzdi7zfstc":["nobody-64","Mr-Nobody"],
"r5fvugallzwk7ou2torktrvm":"nobody000223",
"dhvwurkqy2tos4maq3cszoez":"nobnob",
"sa6rymq33wau2bqa6xjhglum":["nobusumimishima","N.M."],
"t4bsdjuiizt6htqhvjcuain4":["noblenobull","Noble No Bull … "],
"artfcc7uicewvcivgpbfg5fj":["noblenueble","Noodle"],
"lgyzagvjhbaxwd5ibss356v2":"nobodysfool",
"4afsmq3gc6cnreqyson3owmo":"nobody2811",
"slwcimdtwfuhbrme5d6qwb55":["nobodysfriend","Sascha"],
"tzw2lxtmbdu6u65ddspmym76":"nobot",
"5snzxhxzknn43nrtug53zzjx":"nobelwinner",
"3okipyr5ri5zetwnzx5lv5k5":["nobarsdom","NBD"],
"7umxsiwv5jwrhwond6it3iam":"nobuto",
"rujunz336yaqflnc6pooyssz":"nobody2",
"qjqzrdwzxugfvzdjim356kde":["nobrakeeee","크리스탈"],
"ooq5bp3txvm2uqvb7ktbu3rh":["nobodywashome1","Nobody_Was_There"],
"p5gp7kzv4mt46zbuqqxbmmgl":"nobodyartist",
"jhjfxtdnkrm7z45kad3k4uh6":["nobson","Nobson"],
"4u3xtnkae7thctyv63fpuvnk":["nobodyspecial3","NobodySpecial_3"],
"zdpfjo5464dxbuduc34xxedk":["nobusouji","🦂Spoobu🦂ノブ🦂"],
"raypacb6kbfhmit3m7bn7dii":["nobodyfamous","NobodyFamous"],
"uzte5u75vxtqh7mc7scdemxi":["nobodyhere2003","Nobody Here 🔞"],
"2bw2xedixjxwdqfc2v2ahmhk":"nobby24",
"3nrsirbrega5kslhar6v2nnu":["noborissblue","のぼり"],
"7g3u63hlcolj2pzcn5mzab2u":"noballs",
"awylhkbfdf6e3ehpucppbtt7":"noblemissbennet",
"mdfpprcoi6dmq4fkeuhwhj2p":["nobbiexd99","nobbieXD99"],
"n3pp4czgy4xjk7eyvqeynpjh":["noboorinthings","Nob00rus🍤"],
"gl4to3vx3j7lsoq2umjzlw42":["noblechonk","Noble Chonk"],
"tnmgfevgu6m5hwmaspk6pzoj":"nobless",
"ul22mnvh2nldsiw5arlhpo4i":"nobodysystem",
"3rvnbnavdbwdxna2y3inld6a":["nobreath","No_Breath"],
"n4y5iwvow3hzcpp5ca3zhg72":["nobita10094","蒟蒻"],
"impsstopxzziqjzdyqgw7u5n":["noblesatirist","Lord Fred "],
"3ox7h4ckg34pxhqany26mxx6":"nobodyy25",
"dwmwndb4z5ldw4scw4ofrvro":["nobokeisbebsiok","shey (olls)"],
"cpogxmd63k3oojfflnsfa5zn":["nobodybasically","nobodybasically (Joseph D'Amico)"],
"vncztrfj6x43qtlayns62hrs":"noblelilium",
"fia2zg4uknsjq4kpaxpxobdz":["nobodysbabynow","vee m."],
"j3vbn4g4jvohb7r4vhrftdif":"nobodygmd",
"26tssodxekhwmqyoeltufwrt":"nobertoana",
"l5xh6zznzqgcst3wm3x6grve":["noblepirate","Red_Devil🔥Fire_Dragon🇺🇦❤️‍🩹🇮🇱"],
"obvoep3ttkxe75v5nrrl2il4":["nobuwani","wanico"],
"3tvuu3iocnbqh7oa7g6kxftb":["noburu","Noburu"],
"7vdkkhxiezjnv4qqy5g4b6b6":"nobischnitzler",
"2nxtgu64spdnlj3nwvuzd4b2":["nobbertsons","male milf"],
"z4la2p3l5zeuuk5epjs2i6fh":"nobody1987",
"kjngvgzk7rgessycbcl7hniv":["nobrainzane","zane"],
"755fq6jd3pxtcidfkdo44yfp":["nobutnothanks","Nobutnothanks"],
"4oxyvoxb7r4pk5eppulc6kx2":"nobilismendax",
"fkxkpfwqvpbwsgxwi2rkhqx3":"nobsw",
"jp7u5nq4fq4p5v7o55jb4h52":"nobbersly",
"mzuibfu4qplss6no3rrtmtqy":["nobinaryvampire","Crowley"],
"pnswpb3iow23uhnykelkdt6j":["nobleroguelib","Cory (she/her) 🏳️‍🌈"],
"iyt2zcbkto4t5u26nrhzrlmc":"nobodysprincess",
"qbdp2n2ek7mqd5dw2n22ne47":"nobrainerbud",
"upihvyi5nn7zmdbhccadok6o":["nobynobi02","nobynobi02 "],
"gkd2owlqiy22yfpm2cfj2nz7":"noboruma",
"zg6qleqorjcorzkdojf6gjtp":"nobodyxebeche",
"pd2qedzmnfdvnoyk355zj5ok":["nobleknight","NobleKnight"],
"lq5if2ubh3vkwbci4shxelv6":["noboru-meguseka","ノボルン"],
"6ls32mejfgfqs7zhge6zam5b":"nobodyast",
"cpr5b6mu7n4rdkz4qw26ejfg":["nobleteaasmr","NobleTeaASMR"],
"yrmoz7szc32fapy7wyblv6k7":["nobu33","Nobu "],
"64imew23j3uiv5q7bpsizxn3":["nobudannyguy","NobuDannyGuy"],
"sxr2br6c3gqnmy2vv3klsvdj":["nobodyandall","NobodyAndAll"],
"hy3rqzeyhqoelcqf4mysif4e":"nobitanobiiiii",
"4tfxmbouurgce4znjxsz3ua6":"noblueballs",
"sdqrf73c6r3xu3sxsncb64yt":"noblebritt",
"zmqv3fqirnszj636e3f2o65k":"nobbynobbs",
"gnerghjufp4lgjue5bsaymwb":"noble4149",
"hom35qhxadhegkuudgwuge7n":["nobelium","MNG"],
"angotdmx34l3qgla3khptjys":["nobodyshere","Stab Binary Gender - 🏳️‍⚧️"],
"3ruimlmuyum3kw7635m7f3rl":["nobleikeh","Noble Ikeh"],
"37kb6p4oeplf3djtspa3xt73":"nobarsteve",
"p7ljvyv6vnzhlklbti6uhm5n":"nobusada",
"vmcxsigznlodly3nczpbjppf":"nobelundrausch",
"t2wq3ih35gdb2pk6tz3h2zfo":"nobeeasy",
"kuzyqvx4hxqua73nrix4ld3k":"nobled",
"f37n75ryxgbsnz3cya4h26tp":["nseki","Nobuhiro Nob Seki"],
"oa7v22jlrga3kpd7um6h6gdg":["ntsuji","辻 伸弘 (nobuhiro tsuji)"],
"oos52otsdf2fncbsd3afaylz":["nwtnb","WATANABE, Nobuyuki"],
"rhyip4brqsmr6ri4pud4yqh2":["nwtthimble","Nobody Wants the Thimble"],
"vx2dne7xo7wy42wma3ibzpfg":["nyaneon","neon, noble gas"],
"eqjzeqjjgfpoj7gzpbflzkce":["nyasunaga","Nobuaki Yasunaga"],
"4k33k25j2gjj4zrjhd4ghptw":["oamnp","nobodyactuallycares"],
"ew6gkkutpwlylyjlm7hlgxjq":["obiw4nshinobi","OBiW4NSHiNOBi"],
"6zdviumbg4zljcr53xufmiar":["obi-nob-kenobi","Hazel"],
"tey3w4hlnzveb4vf2ywjtq7h":["oftenmiserable","The noble Lord Christopher of Marston Moretaine🇪🇺🇬🇧🇧🇬"],
"fvbeksq76c4tvy5c3332gfao":["ogoh","Nobuaki Ogoh"],
"hwyjvazffvqzpasv2r7e6bbd":["olcurmudgeon","D. Noble"],
"75hhkusa7sylikccdciksemw":["olddaddyp","Some random nobody"],
"35vnc2tzbojxcuy6fzwvv3em":["onbuyu","nobu"],
"io7ebcj66ez63grw26agdcoy":["osawaru","Noble"],
"uu7ylhh4475ezrudu5lcw6fi":["pauletteperrynoble","Paulette Perry Noble"],
"bzpyoamotyiove2s3mp2nat3":["pawnerd","Noboru aka Pawnerd! "],
"e3s4kf5nguztf73xtoi7zheo":["patiencenoble","Patience Noble, writer"],
"nx5lvubxyt5thwmmlfo26vos":["petbugs13","nobody"],
"l7tzcprpkzgjmo3lfln6eitg":["persianwarrior","Nobody Cares"],
"ire7t5hlbfkex2rkrcv4ypzr":["philnobilejr","Phil Nobile Jr."],
"iyojyqzstdlslpdzpa7xkc7e":["poppawhitelow","Nobody Important "],
"svoizwy5mp6q4ol6j2pu74we":["prismbeings.com","noby"],
"ky2lkcbx5dldymopqgyqt62q":["professornobu","Professor Nobu"],
"z6bifruijmguhzzm7a2wb5ai":["ptnobel","Parth Nobel"],
"v5fc6oy6hahrjrnaxyyhl3nu":["public15894466","Nobody"],
"7znw2g3vnk2qtl3foruwfzu7":["purenobody101","Nobody ☧"],
"ypiwc4rgkmhb2twnqoahmr2y":["pupnobo","Pup_Nobo"],
"5dn5vl2cvfgrzqlegb2f4y5x":["pupnoble","Pup Noble"],
"qa3qnsspc7zd6534x2r4yxsz":["raf","Raf Noboa y Rivera"],
"rj53igw6326257nc2oflq376":["raiders","Nemo Nobody"],
"colaqmmep74lt5w4svo5rdyh":["raver1975","Nobody"],
"qld3u4tmqyhtzolxub2zrdzh":["rcnoble","Russell Noble"],
"sthdrqg33yq6ffo6krhkost4":["reggie","reggie noble"],
"3waxpumdf7bxb72ozq72bgj4":["remrkblyrandom","Some Random Nobody"],
"e3czsabrb47cshwnitmj5q7r":["reynoble","Rey Noble✨"],
"e6ylyqodhqf7vrbbldnffuet":["ricardonobre","Ricardo Nobre"],
"regrwxeel5vhorqnvt4cmh2x":["robnobody","Rob Nobody "],
"arxjey7gbthz5z34ojck7o2k":["robjohnnoble","Rob Noble"],
"lsmu7dgf4xiot3awhlhyua5v":["roxasth3nobody","FFXIV Miqo'te Monk of badassery"],
"mg44qehpe2ethcdktq5jkisg":["romantimberwolf","Nobo"],
"jeqrgfbjemamfqu2fsifynxj":["rodolfonobrega","Rodolfo Nobrega"],
"ege5muci56bfj5kihn4dre6p":["ryanobles","Ryan Nobles"],
"xgk4ly3jtxdtuzigljklrtjw":["ryaninjapan","Ryan Noble"],
"2ky7pujtsyvz5ysa2sw2yabj":["ryandomonica","Noblood"],
"royoi4q22vh4gqaievc3oug2":["sabaa","Saba nobari"],
"7gxr2iwav6mkf7cdqqsqtulp":["safiyanoble","Safiya Umoja Noble"],
"t4so74q4wfqh54vuag7saxon":["sayumi","nobody ❤︎ sayumi.bsky.social"],
"4p66vhe7musaakd5ambeu6r4":["saxorthenobody","SaXor the Nobody"],
"kgmcj6obc24xvf3ar7iowzh3":["sactaecrucis","Mein Name ist Nobody"],
"k2q4oycp3hvfrhe2wpxhof4e":["sernobs","Nobs"],
"3rxeyvkq6fu5hoigadlvbs2n":["seenoevil","Nobody "],
"6fqxjhqqdelqjpemlxafvzoo":["seishinoboru","Seishin noboru "],
"tvloxclzzbdfuhaxiq3lojz7":["shinoda-senshi","Noble Jones"],
"yo27sym5zeybftzcxg3l5smw":["shireennoble","Shireen Noble"],
"jg74qgw3wil46y6miugxon7f":["shiraku","nobody"],
"e4s2cs3xswhcczefrg3gpauo":["silverkey","Mr.Nobody "],
"kglbw3jve5rdnktslcqn67uf":["sizesupporter","Noboru -  Professional insole"],
"jasoga55bbon6ac2jxjavift":["sneuroble","Stephanie Noble"],
"6pzwbmrg3blwqij25hvdjcfz":["snoble","Steven Klaiber-Noble"],
"nowvy57usffmndt4hha4ylnl":["snowy1256","Dominic Noble"],
"shkhnq5tj2c76u2b3zxhqguv":["somenobody","🌕Just some nobody~🎃"],
"2nwrbgtwgc4kyawpi3c45sgw":["sorcerornobody","Sorceror Nobody"],
"f2u6lqkyegmz6btx3r66crph":["spacebear","mr.Nobody"],
"jwoslys5eg3h6xhgauybbwmo":["spookyscary","Nobody could have predicted this"],
"ulmqdqoaof5rb5wvogmtu2ht":["squishynobones","Squishy Nobones"],
"b2i4bzmud4a2kg722irb4ixz":["srijana","Nobodyisperfect3210"],
"fqa5nunjtbgsufminfv5y5em":["sshboy","Nobody "],
"cdtzwjbynocnjamiis5mr4od":["stefnoble","Stef Noble"],
"nhk254wf3rqtnoa73rkwzcqa":["steve55","Nobody "],
"x2ixjdrwuk3spcfsdd6d35zz":["st4wb3rrysush1","Nobody"],
"frnv5pqqeofvigzh6irhupdj":["stashgong","Noble Savage"],
"vz2sgsrz6c3s7mk3rtcr6pf4":["tatsuyanobori","Tatsuya Nobori"],
"gbxqgoiyii444uc2mbjq66iy":["taurusspirit","Noble"],
"6wot6a7ymk34yfyvkjna3i6k":["tenorleggiero","JustPaulNobodyElse"],
"5wbzem6jswvyv6qsxndoe6vn":["thefatginger","Nobody"],
"mfw24qmr752lr772hi6zcwes":["thenobleopossum","The Noble Opossum"],
"tng6r5zj25x6tiowjffjyfy5":["thenoble1","Eric Noble"],
"hekojpa6keejkiaqhezcdq3u":["thatnobody","That Nobody"],
"czhjxbwmkurzl7cxwygtkyri":["thisisinsane","Nobody"],
"xq2nes2itesneww4inekpp4n":["tinkerbellafrou","Lia - Nobody Important "],
"wdidxxyj6pcjcahgihcipahw":["tkcodes","Nobody"],
"nmrtcpidwu3wme4j4q5ovanj":["toiautrefois","Nobody’s little weasel "],
"pwkk64j3u7o4344mbu5fcus2":["toshnobody","Valentin Stemetz/Tosh Nobody"],
"g7x7tv6dtntvpn3rpdaayq5z":["toomusky4u","NobodyisHere"],
"3knuuvev6sjqbjwn7ksdvrry":["treynobles","Trey Nobles"],
"keymltz2xicuzmpwm6w57bv6":["untroisundeux","Nobody"],
"tcgg6sdw6r53gfal3qmhi3ae":["useurnamenoble","Nobleza 🇵🇷"],
"hn3ryiijpnw2wwbzbn7be5uf":["valentinesfm","Nobles"],
"qh5a6wd2d47mjyfncae5crm4":["veigar","Nobody"],
"st3nqij5ggyq7tyduuws6vqs":["wafflesfriendswork","poetic noble land mermaid"],
"ujjhxf5yag3rxfzguw4vp3ur":["waxrend","Andrew's Nobody"],
"ahlqaopv5ext3wrtb5hsb2bf":["wesleynoble.com","Wesley Noble"],
"kjpy37d4hhm5bkhqo4etiwpt":["westhamunited","Mark Noble Jr."],
"z5giyr2n6n4b2b5z72fnuctl":["whispersongvoid","Mx Nobody"],
"sy7gft7h2ce35quo57edcsuw":["wiseguise","Jeremy Noble"],
"tm6ifv5ts7fkunwxxm3er557":["wnobuo","Willian Nobuo"],
"hdnrtgh2l2lv7nfq5vp7hgen":["wnober","Will Nober"],
"epup4aeqqh3hwxoi24owwut5":["wolfdo.gg","Noble 🐺"],
"2ew4vji4qu7o6dcbuzkw3mcd":["xc3nobite","🖤🦂"],
"3pqumtiara4muqbs26m243om":["xhuth","noble"],
"75l5ucpr3ppjwh33yaxqibiv":["xictrov","Eternal Nobody."],
"sv4k3bu346dv4pffi5bxtpmb":["xomasth"," χom 🐸⚔️ The Froggy Nobody "],
"uqhbciub3cbn37oxadbo5nih":["yellowyorkie","David Nobbs "],
"kbcywurhxp7xv5bddz7obdbe":["yolanim","mr_nobody"],
"mdiqbfvuswbxnk4j2kvzy6qf":["ysendra","Ysen Nobody"],
"lm5pu3tws5zm7oczdcfvk26e":["yuukaze","Joaquim Nobre"],
"zughfxf6baingh4mbnp4wqa4":["zap","nobody"],
"wzdp3a2unofynemer4rcp7fg":["zachbear","Zach Nobody Bear"],
"pyylvnhx4r4c5icm6dc6iqrj":["zetrow","nobody"],
"uljvreovorvxuzz2ke3b3voo":"nobfunt"
}
