{
"fohmxxut3y4425mm2w776bjm":["ahmadalinaqvi","Ahmad Ali Naqvi"],
"2jehw6iwwnqqomzcnmi5zm2w":["ahadnaqvi","Ahad Ali Naqvi"],
"la3drtqwcset5rnctm3cy53p":["alinaqvipro","Ali Naqvi"],
"pjpgrwtqukraoao7wobopbgj":["anaqvi","A Naqvi"],
"miagoht3bgk5mergmnspktbs":["asjadnaqvi","Asjad Naqvi"],
"vnvi6awkokbrtchijj73vxwb":["cozytoes","Naq"],
"xxltv4jwinson4qs2qzbqwei":["emerald-truth","naq"],
"hn7pcl2p4y3dchepscjtje2m":["g3naq","🍞"],
"zze3d7gsrvkw3ca25nthdgsf":["hanisarrt","Hani Naqi"],
"do6dmi7eawene6kwf5bkuua6":["hindb","Hind Bellouk Al Naqbi"],
"6g5rjipe5ft44ksa4z4pdouw":["humanaqvi","Huma Naqvi"],
"2vqws4jzwtquwcocniqj5mee":["loupnaqala","Le loup de Naqala"],
"qrmnlcfeagx3dxrr5d36ry5z":["naqme","naQme"],
"cowwns3lis4q57rvxkcja24t":["naqvi","Shaheer Naqvi"],
"pvlrkqkhhfh3absjhka2aima":["naqvitalha","Talha Naqvi "],
"4yoinaoymxezgdsevkdt2prc":["naqajima","naqajima"],
"sqszymnyfmnnhpx7hdpy4zns":["naqhmeeee","نیکی"],
"t57cmywmdzp3oxizfwna3ghs":"naquadria",
"tgduvqsui6sksj2ydqq7aohv":["naqfox","Naq"],
"ijdrbrml5xbp2z4jreaz5wgh":["naq24-may33-myaw33","Sylvia"],
"ewjgod7syi5k7opwvvtfkwdr":"naquep",
"xjarshj4pmdzkete2lgx5gu6":["naqiy","Naqiy Mcmullen "],
"3t67hm6oeysyxo2qg2xbnzf6":["naqt","NAQT"],
"x4poweutpualvttdp2lrvjlb":["naqai","Nakai"],
"pdoa7rqgbpap4vyepq7lcmyq":"naqvima",
"yisqoyj2q22dhx5qymojouu6":["naquax","Sascha"],
"37uswy7tbwkdh7r7rr7krxgi":"naqx",
"vodvjwfaku3pdpjohxijffr5":["naqtlive","NAQT Live!"],
"azr2l4so43h4szdbbgljn36p":"naquia",
"42p2ywemp7ibzeu2lab3cs3c":["nn879","Nadia Naqib "],
"zds6qekwdkila42fl2hg6vpd":["nullsurface","Cameron Higby-Naquin"],
"bbnox7z3mxykljb5zhsmj6dy":["rodjnaquin","Rod J. Naquin"],
"ffae3yj5rpirmi3e5xzkw6af":["sahinnaqvi","Sahin Naqvi"]
}
